tictactoe/__init__.py
tictactoe/egtb.py
tictactoe/py.typed
python_tictactoe-0.0.7.dist-info/LICENSE
python_tictactoe-0.0.7.dist-info/METADATA
python_tictactoe-0.0.7.dist-info/WHEEL
python_tictactoe-0.0.7.dist-info/top_level.txt
python_tictactoe-0.0.7.dist-info/RECORD
