Metadata-Version: 2.1
Name: python-tictactoe
Version: 0.0.7
Summary: A tic-tac-toe library that supports different sizes and dimensions and how many marks in a row to win
Home-page: https://github.com/AttackingOrDefending/python-tictactoe
Author: AttackingOrDefending
Project-URL: Bug Tracker, https://github.com/AttackingOrDefending/python-tictactoe/issues
Keywords: tic-tac-toe,tictactoe,game
Classifier: Intended Audience :: Developers
Classifier: Intended Audience :: Science/Research
Classifier: Programming Language :: Python :: 3
Classifier: License :: OSI Approved :: MIT License
Classifier: Operating System :: OS Independent
Classifier: Topic :: Games/Entertainment :: Turn Based Strategy
Classifier: Topic :: Software Development :: Libraries :: Python Modules
Requires-Python: >=3.6
License-File: LICENSE
